ubatch/__init__.py
ubatch/data_request.py
ubatch/decorators.py
ubatch/py.typed
ubatch/ubatch.py
ubatch-1.0.0.dist-info/WHEEL
ubatch-1.0.0.dist-info/METADATA
ubatch-1.0.0.dist-info/RECORD
