Metadata-Version: 2.1
Name: ubatch
Version: 1.0.0
Summary: Micro batch solution for improve throughput in SIMD processes
Home-page: https://github.com/mercadolibre/ubatch
License: Apache-2.0
Author: Rodolfo E. Edelmann
Author-email: redelmann@mercadolibre.com
Maintainer: Leandro E. Colombo Viña
Maintainer-email: leandro.colombo@mercadolibre.com
Requires-Python: >=3.6,<4.0
Classifier: Intended Audience :: Developers
Classifier: License :: OSI Approved :: Apache Software License
Classifier: Programming Language :: Python
Classifier: Programming Language :: Python :: 3
Classifier: Programming Language :: Python :: 3.6
Classifier: Programming Language :: Python :: 3.7
Classifier: Programming Language :: Python :: 3.8
Classifier: Programming Language :: Python :: 3.9
Provides-Extra: benchmark
Provides-Extra: docs
Requires-Dist: Sphinx (>=3.3,<4.0); extra == "docs"
Requires-Dist: flask-restx (>=0.2,<0.3); extra == "benchmark"
Requires-Dist: gunicorn (>=20.0,<21.0); extra == "benchmark"
Requires-Dist: keras (>=2.4,<3.0); extra == "benchmark"
Requires-Dist: recommonmark (>=0.6,<0.7); extra == "docs"
Requires-Dist: scikit-learn (>=0.23,<0.24); extra == "benchmark"
Requires-Dist: sphinx-autodoc-typehints (>=1.11,<2.0); extra == "docs"
Requires-Dist: sphinx_rtd_theme (>=0.5,<0.6); extra == "docs"
Requires-Dist: tensorflow (>=2.3,<3.0); extra == "benchmark"
Requires-Dist: xgboost (>=1.2,<2.0); extra == "benchmark"
Project-URL: Bug Tracker, https://github.com/mercadolibre/ubatch/issues
Project-URL: Repository, https://github.com/mercadolibre/ubatch
